streamlit_community_navigation_bar/__init__.py
streamlit_community_navigation_bar-4.7.8.dist-info/licenses/LICENSE
streamlit_navigation_bar/__init__.py
streamlit_navigation_bar/__main__.py
streamlit_navigation_bar/errors.py
streamlit_navigation_bar/example.py
streamlit_navigation_bar/logo.svg
streamlit_navigation_bar/match_navbar.py
streamlit_navigation_bar/frontend/.gitignore
streamlit_navigation_bar/frontend/README.md
streamlit_navigation_bar/frontend/env.d.ts
streamlit_navigation_bar/frontend/index.html
streamlit_navigation_bar/frontend/package-lock.json
streamlit_navigation_bar/frontend/package.json
streamlit_navigation_bar/frontend/tsconfig.app.json
streamlit_navigation_bar/frontend/tsconfig.json
streamlit_navigation_bar/frontend/tsconfig.node.json
streamlit_navigation_bar/frontend/vite.config.ts
streamlit_navigation_bar/frontend/.vscode/extensions.json
streamlit_navigation_bar/frontend/dist/index.html
streamlit_navigation_bar/frontend/dist/assets/index--vjNFBar.js
streamlit_navigation_bar/frontend/dist/assets/index-CundAqef.css
streamlit_navigation_bar/frontend/src/App.vue
streamlit_navigation_bar/frontend/src/StNavbar.vue
streamlit_navigation_bar/frontend/src/main.ts
streamlit_navigation_bar/frontend/src/streamlit/StreamlitVue.ts
streamlit_navigation_bar/frontend/src/streamlit/WithStreamlitConnection.vue
streamlit_navigation_bar/frontend/src/streamlit/index.ts
streamlit_navigation_bar/templates/base.css
streamlit_navigation_bar/templates/options.css
streamlit_community_navigation_bar-4.7.8.dist-info/METADATA
streamlit_community_navigation_bar-4.7.8.dist-info/WHEEL
streamlit_community_navigation_bar-4.7.8.dist-info/entry_points.txt
streamlit_community_navigation_bar-4.7.8.dist-info/top_level.txt
streamlit_community_navigation_bar-4.7.8.dist-info/RECORD
